csv2excel/__init__.py
csv2excel/csv2excel.py
csv2geojson/__init__.py
csv2geojson/csv2geojson.py
gisconflation/__init__.py
gisconflation/csv2gecodedcsv.py
gisconflation/csvedit.py
gisconflation/dictionarybuilder.py
gisconflation/dictionarymerger.py
gisconflation/geojsonconcat.py
gisconflation/geojsondiff.py
gisconflation/geojsonedit.py
gisconflation/geojsonmerger.py
gisconflation/json2csv.py
gisconflation/osmf2geojson.py
gisconflation/overpassql2osmf.py
gisconflation/util.py
gisconflation/lib/__init__.py
gisconflation/lib/language.py
gis_conflation_toolchain-0.7.2.dist-info/LICENSE
gis_conflation_toolchain-0.7.2.dist-info/METADATA
gis_conflation_toolchain-0.7.2.dist-info/WHEEL
gis_conflation_toolchain-0.7.2.dist-info/entry_points.txt
gis_conflation_toolchain-0.7.2.dist-info/top_level.txt
gis_conflation_toolchain-0.7.2.dist-info/RECORD
