Metadata-Version: 2.1
Name: gis-conflation-toolchain
Version: 0.7.2
Summary: gis-conflation-toolchain
Home-page: https://github.com/fititnt/spatial-data-conflation-open-toolchain
Author: Emerson Rocha
Author-email: rocha@ieee.org
Project-URL: Bug Tracker, https://github.com/fititnt/spatial-data-conflation-open-toolchain/issues
Classifier: Programming Language :: Python :: 3
Classifier: License :: OSI Approved :: GNU Affero General Public License v3 or later (AGPLv3+)
Classifier: Operating System :: OS Independent
Classifier: Typing :: Typed
Classifier: Topic :: Utilities
Requires-Python: >=3.8
License-File: LICENSE
Requires-Dist: shapely
Requires-Dist: haversine
Requires-Dist: pandas
Requires-Dist: levenshtein
Provides-Extra: extras
Requires-Dist: geocoder ; extra == 'extras'
